{"expireTime":9007200860356172000,"key":"contentful-sync-data-p374xccizkxs-master","val":{"entries":[{"sys":{"space":{"sys":{"type":"Link","linkType":"Space","id":"p374xccizkxs"}},"id":"2K1ISVprh78ZLtp3mKvA7i","type":"Entry","createdAt":"2020-11-15T07:44:52.941Z","updatedAt":"2020-11-17T09:04:31.245Z","environment":{"sys":{"id":"master","type":"Link","linkType":"Environment"}},"revision":5,"contentType":{"sys":{"type":"Link","linkType":"ContentType","id":"courses"}}},"fields":{"title":{"en-US":"XYZ"},"category":{"en-US":"web"},"description":{"en-US":"Up for testing! Yes It's Working\n"},"price":{"en-US":10.99},"image":{"en-US":{"sys":{"type":"Link","linkType":"Asset","id":"2e3YexE0Yh2Yytdo19ChGs"}}}}},{"sys":{"space":{"sys":{"type":"Link","linkType":"Space","id":"p374xccizkxs"}},"id":"3NFZ8sFnq8AuhlZYClHjGK","type":"Entry","createdAt":"2020-11-15T12:34:05.591Z","updatedAt":"2020-11-17T09:06:27.211Z","environment":{"sys":{"id":"master","type":"Link","linkType":"Environment"}},"revision":3,"contentType":{"sys":{"type":"Link","linkType":"ContentType","id":"courses"}}},"fields":{"title":{"en-US":"XYZ"},"category":{"en-US":"mobile"},"description":{"en-US":"Up for testing! Yes It's Working\n"},"price":{"en-US":18},"image":{"en-US":{"sys":{"type":"Link","linkType":"Asset","id":"3ndA4nnMP2KHxJRrqxmpyy"}}}}},{"sys":{"space":{"sys":{"type":"Link","linkType":"Space","id":"p374xccizkxs"}},"id":"1Ggn0K5W7KQju0JZly1GfQ","type":"Entry","createdAt":"2020-11-12T17:47:14.988Z","updatedAt":"2020-11-17T09:07:36.020Z","environment":{"sys":{"id":"master","type":"Link","linkType":"Environment"}},"revision":5,"contentType":{"sys":{"type":"Link","linkType":"ContentType","id":"courses"}}},"fields":{"title":{"en-US":"XYZ"},"category":{"en-US":"web"},"description":{"en-US":"Up for testing! Yes It's Working\n"},"price":{"en-US":9.99},"image":{"en-US":{"sys":{"type":"Link","linkType":"Asset","id":"3ckVo2irdREEcN8PsDFr58"}}}}},{"sys":{"space":{"sys":{"type":"Link","linkType":"Space","id":"p374xccizkxs"}},"id":"7HvMxTwN0y4eDvV0PHC0sh","type":"Entry","createdAt":"2020-11-12T14:14:45.099Z","updatedAt":"2020-11-15T07:21:47.850Z","environment":{"sys":{"id":"master","type":"Link","linkType":"Environment"}},"revision":2,"contentType":{"sys":{"type":"Link","linkType":"ContentType","id":"courses"}}},"fields":{"title":{"en-US":"Django "},"category":{"en-US":"web"},"description":{"en-US":"Create 8 projects in Django BY Yash chauhan"},"price":{"en-US":11},"image":{"en-US":{"sys":{"type":"Link","linkType":"Asset","id":"4FDCzxFykt9GTHUSnFYtKV"}}}}},{"sys":{"space":{"sys":{"type":"Link","linkType":"Space","id":"p374xccizkxs"}},"id":"6hFK6Ky2I6nL1BzNaeurGq","type":"Entry","createdAt":"2020-11-12T14:24:44.706Z","updatedAt":"2020-11-12T14:24:44.706Z","environment":{"sys":{"id":"master","type":"Link","linkType":"Environment"}},"revision":1,"contentType":{"sys":{"type":"Link","linkType":"ContentType","id":"bundles"}}},"fields":{"title":{"en-US":"NodeJS bundle"},"price":{"en-US":17},"image":{"en-US":{"sys":{"type":"Link","linkType":"Asset","id":"lionI6UJHtQy28zi6Bbud"}}}}},{"sys":{"space":{"sys":{"type":"Link","linkType":"Space","id":"p374xccizkxs"}},"id":"2v2hJureHW7DcD88yG1tyn","type":"Entry","createdAt":"2020-11-12T14:16:54.023Z","updatedAt":"2020-11-12T14:16:54.023Z","environment":{"sys":{"id":"master","type":"Link","linkType":"Environment"}},"revision":1,"contentType":{"sys":{"type":"Link","linkType":"ContentType","id":"bundles"}}},"fields":{"title":{"en-US":"Android bundle"},"price":{"en-US":16},"image":{"en-US":{"sys":{"type":"Link","linkType":"Asset","id":"4IrKHr5rirNWlcaEClTyLP"}}}}}],"assets":[{"sys":{"space":{"sys":{"type":"Link","linkType":"Space","id":"p374xccizkxs"}},"id":"3ndA4nnMP2KHxJRrqxmpyy","type":"Asset","createdAt":"2020-11-15T12:32:55.125Z","updatedAt":"2020-11-17T09:06:21.013Z","environment":{"sys":{"id":"master","type":"Link","linkType":"Environment"}},"revision":2},"fields":{"title":{"en-US":"xyz"},"file":{"en-US":{"url":"//images.ctfassets.net/p374xccizkxs/3ndA4nnMP2KHxJRrqxmpyy/ac0c3ef68af3447983708a2056d795ea/2.png","details":{"size":1118111,"image":{"width":1024,"height":576}},"fileName":"2.png","contentType":"image/png"}}}},{"sys":{"space":{"sys":{"type":"Link","linkType":"Space","id":"p374xccizkxs"}},"id":"2e3YexE0Yh2Yytdo19ChGs","type":"Asset","createdAt":"2020-11-15T07:44:46.461Z","updatedAt":"2020-11-17T09:04:06.148Z","environment":{"sys":{"id":"master","type":"Link","linkType":"Environment"}},"revision":2},"fields":{"title":{"en-US":"xyz"},"file":{"en-US":{"url":"//images.ctfassets.net/p374xccizkxs/2e3YexE0Yh2Yytdo19ChGs/81459f0d0be86c21bf0951e2c3225148/1.png","details":{"size":532218,"image":{"width":1024,"height":576}},"fileName":"1.png","contentType":"image/png"}}}},{"sys":{"space":{"sys":{"type":"Link","linkType":"Space","id":"p374xccizkxs"}},"id":"3ckVo2irdREEcN8PsDFr58","type":"Asset","createdAt":"2020-11-12T17:46:47.533Z","updatedAt":"2020-11-17T09:07:20.918Z","environment":{"sys":{"id":"master","type":"Link","linkType":"Environment"}},"revision":2},"fields":{"title":{"en-US":"xyz"},"file":{"en-US":{"url":"//images.ctfassets.net/p374xccizkxs/3ckVo2irdREEcN8PsDFr58/b04c395a6d403c4098fd437cca4adcc8/3.png","details":{"size":1095686,"image":{"width":1024,"height":576}},"fileName":"3.png","contentType":"image/png"}}}},{"sys":{"space":{"sys":{"type":"Link","linkType":"Space","id":"p374xccizkxs"}},"id":"lionI6UJHtQy28zi6Bbud","type":"Asset","createdAt":"2020-11-12T14:17:26.837Z","updatedAt":"2020-11-12T14:17:26.837Z","environment":{"sys":{"id":"master","type":"Link","linkType":"Environment"}},"revision":1},"fields":{"title":{"en-US":"nodejs"},"file":{"en-US":{"url":"//images.ctfassets.net/p374xccizkxs/lionI6UJHtQy28zi6Bbud/3d916f49ef39632ca936f9f0ea138e01/nodeB.png","details":{"size":260965,"image":{"width":1024,"height":576}},"fileName":"nodeB.png","contentType":"image/png"}}}},{"sys":{"space":{"sys":{"type":"Link","linkType":"Space","id":"p374xccizkxs"}},"id":"4IrKHr5rirNWlcaEClTyLP","type":"Asset","createdAt":"2020-11-12T14:16:49.679Z","updatedAt":"2020-11-12T14:16:49.679Z","environment":{"sys":{"id":"master","type":"Link","linkType":"Environment"}},"revision":1},"fields":{"title":{"en-US":"adroidbundle"},"file":{"en-US":{"url":"//images.ctfassets.net/p374xccizkxs/4IrKHr5rirNWlcaEClTyLP/d8c31a129f946c3e40b387b1fdd8cd01/AB.png","details":{"size":262769,"image":{"width":1024,"height":576}},"fileName":"AB.png","contentType":"image/png"}}}},{"sys":{"space":{"sys":{"type":"Link","linkType":"Space","id":"p374xccizkxs"}},"id":"4FDCzxFykt9GTHUSnFYtKV","type":"Asset","createdAt":"2020-11-12T14:14:35.604Z","updatedAt":"2020-11-12T14:14:35.604Z","environment":{"sys":{"id":"master","type":"Link","linkType":"Environment"}},"revision":1},"fields":{"title":{"en-US":"django"},"file":{"en-US":{"url":"//images.ctfassets.net/p374xccizkxs/4FDCzxFykt9GTHUSnFYtKV/507cf29e189e61f41ed04740c3ad311b/django.png","details":{"size":447225,"image":{"width":1024,"height":576}},"fileName":"django.png","contentType":"image/png"}}}}]}}